{"r5.4xlarge":{"hourly_rate":0.684,"upfront_rate":0.0},"c5.4xlarge":{"hourly_rate":0.407,"upfront_rate":0.0},"t3.nano":{"hourly_rate":0.0073,"upfront_rate":0.0},"r5.xlarge":{"hourly_rate":0.203,"upfront_rate":0.0},"m5.12xlarge":{"hourly_rate":1.553,"upfront_rate":0.0},"t3.small":{"hourly_rate":0.0242,"upfront_rate":0.0},"r5.12xlarge":{"hourly_rate":1.944,"upfront_rate":0.0},"r5.24xlarge":{"hourly_rate":3.835,"upfront_rate":0.0},"i3.xlarge":{"hourly_rate":0.242,"upfront_rate":0.0},"i3.2xlarge":{"hourly_rate":0.45,"upfront_rate":0.0},"c5.2xlarge":{"hourly_rate":0.22,"upfront_rate":0.0},"t3.large":{"hourly_rate":0.0749,"upfront_rate":0.0},"m5.24xlarge":{"hourly_rate":3.072,"upfront_rate":0.0},"c5.18xlarge":{"hourly_rate":1.715,"upfront_rate":0.0},"m5.xlarge":{"hourly_rate":0.16,"upfront_rate":0.0},"r5.2xlarge":{"hourly_rate":0.369,"upfront_rate":0.0},"m5.2xlarge":{"hourly_rate":0.286,"upfront_rate":0.0},"m5.4xlarge":{"hourly_rate":0.54,"upfront_rate":0.0},"t3.medium":{"hourly_rate":0.0485,"upfront_rate":0.0},"c5.xlarge":{"hourly_rate":0.126,"upfront_rate":0.0},"i3.16xlarge":{"hourly_rate":3.371,"upfront_rate":0.0},"i3.large":{"hourly_rate":0.137,"upfront_rate":0.0},"m5.large":{"hourly_rate":0.096,"upfront_rate":0.0},"c5.large":{"hourly_rate":0.08,"upfront_rate":0.0},"i3.4xlarge":{"hourly_rate":0.868,"upfront_rate":0.0},"r5.large":{"hourly_rate":0.101,"upfront_rate":0.0},"t3.micro":{"hourly_rate":0.0106,"upfront_rate":0.0},"c5.9xlarge":{"hourly_rate":0.874,"upfront_rate":0.0},"t3.xlarge":{"hourly_rate":0.1508,"upfront_rate":0.0},"t3.2xlarge":{"hourly_rate":0.2657,"upfront_rate":0.0},"i3.8xlarge":{"hourly_rate":1.702,"upfront_rate":0.0}}