{"d2.2xlarge":{"hourly_rate":0.805,"upfront_rate":0.0},"t2.large":{"hourly_rate":0.0741,"upfront_rate":0.0},"m5.4xlarge":{"hourly_rate":1.125,"upfront_rate":0.0},"p2.xlarge":{"hourly_rate":0.712,"upfront_rate":0.0},"m5.xlarge":{"hourly_rate":0.281,"upfront_rate":0.0},"h1.8xlarge":{"hourly_rate":2.512,"upfront_rate":0.0},"r4.8xlarge":{"hourly_rate":2.5252,"upfront_rate":0.0},"m4.large":{"hourly_rate":0.1417,"upfront_rate":0.0},"m5a.large":{"hourly_rate":0.135,"upfront_rate":0.0},"r5.24xlarge":{"hourly_rate":7.571,"upfront_rate":0.0},"p3dn.24xlarge":{"hourly_rate":20.927,"upfront_rate":0.0},"r5ad.4xlarge":{"hourly_rate":1.276,"upfront_rate":0.0},"r5.xlarge":{"hourly_rate":0.315,"upfront_rate":0.0},"c4.4xlarge":{"hourly_rate":1.143,"upfront_rate":0.0},"p3.2xlarge":{"hourly_rate":2.163,"upfront_rate":0.0},"m5d.4xlarge":{"hourly_rate":1.191,"upfront_rate":0.0},"d2.4xlarge":{"hourly_rate":1.529,"upfront_rate":0.0},"r5.4xlarge":{"hourly_rate":1.262,"upfront_rate":0.0},"t3.xlarge":{"hourly_rate":0.1562,"upfront_rate":0.0},"h1.16xlarge":{"hourly_rate":5.024,"upfront_rate":0.0},"r4.2xlarge":{"hourly_rate":0.6313,"upfront_rate":0.0},"m5a.2xlarge":{"hourly_rate":0.542,"upfront_rate":0.0},"i3.4xlarge":{"hourly_rate":1.432,"upfront_rate":0.0},"p2.8xlarge":{"hourly_rate":5.695,"upfront_rate":0.0},"m5a.12xlarge":{"hourly_rate":3.251,"upfront_rate":0.0},"i3.16xlarge":{"hourly_rate":5.726,"upfront_rate":0.0},"r4.4xlarge":{"hourly_rate":1.2626,"upfront_rate":0.0},"m4.10xlarge":{"hourly_rate":2.8336,"upfront_rate":0.0},"m4.xlarge":{"hourly_rate":0.2834,"upfront_rate":0.0},"t3.medium":{"hourly_rate":0.039,"upfront_rate":0.0},"c4.large":{"hourly_rate":0.143,"upfront_rate":0.0},"c4.8xlarge":{"hourly_rate":2.471,"upfront_rate":0.0},"c5n.18xlarge":{"hourly_rate":4.938,"upfront_rate":0.0},"m5ad.4xlarge":{"hourly_rate":1.152,"upfront_rate":0.0},"z1d.3xlarge":{"hourly_rate":1.081,"upfront_rate":0.0},"x1.16xlarge":{"hourly_rate":5.409,"upfront_rate":0.0},"r5d.24xlarge":{"hourly_rate":7.975,"upfront_rate":0.0},"p3.8xlarge":{"hourly_rate":8.65,"upfront_rate":0.0},"x1e.4xlarge":{"hourly_rate":1.969,"upfront_rate":0.0},"x1e.8xlarge":{"hourly_rate":3.938,"upfront_rate":0.0},"t3.nano":{"hourly_rate":0.0072,"upfront_rate":0.0},"c5d.xlarge":{"hourly_rate":0.277,"upfront_rate":0.0},"r5d.12xlarge":{"hourly_rate":3.988,"upfront_rate":0.0},"r5d.2xlarge":{"hourly_rate":0.665,"upfront_rate":0.0},"i3.8xlarge":{"hourly_rate":2.863,"upfront_rate":0.0},"g3.4xlarge":{"hourly_rate":1.4042,"upfront_rate":0.0},"m5ad.xlarge":{"hourly_rate":0.288,"upfront_rate":0.0},"c5.9xlarge":{"hourly_rate":2.395,"upfront_rate":0.0},"c5d.2xlarge":{"hourly_rate":0.553,"upfront_rate":0.0},"m5d.metal":{"hourly_rate":7.146,"upfront_rate":0.0},"c5d.9xlarge":{"hourly_rate":2.49,"upfront_rate":0.0},"i3.large":{"hourly_rate":0.179,"upfront_rate":0.0},"r5ad.24xlarge":{"hourly_rate":7.655,"upfront_rate":0.0},"r4.16xlarge":{"hourly_rate":5.0504,"upfront_rate":0.0},"t2.xlarge":{"hourly_rate":0.1332,"upfront_rate":0.0},"r5d.xlarge":{"hourly_rate":0.332,"upfront_rate":0.0},"x1e.16xlarge":{"hourly_rate":7.877,"upfront_rate":0.0},"c5n.9xlarge":{"hourly_rate":2.469,"upfront_rate":0.0},"r5a.large":{"hourly_rate":0.151,"upfront_rate":0.0},"r5.12xlarge":{"hourly_rate":3.785,"upfront_rate":0.0},"h1.2xlarge":{"hourly_rate":0.628,"upfront_rate":0.0},"m5a.4xlarge":{"hourly_rate":1.084,"upfront_rate":0.0},"r5a.12xlarge":{"hourly_rate":3.623,"upfront_rate":0.0},"r5ad.2xlarge":{"hourly_rate":0.638,"upfront_rate":0.0},"g3s.xlarge":{"hourly_rate":0.687,"upfront_rate":0.0},"t2.nano":{"hourly_rate":0.0052,"upfront_rate":0.0},"t3.small":{"hourly_rate":0.0287,"upfront_rate":0.0},"z1d.large":{"hourly_rate":0.18,"upfront_rate":0.0},"m5.24xlarge":{"hourly_rate":6.753,"upfront_rate":0.0},"m5ad.12xlarge":{"hourly_rate":3.455,"upfront_rate":0.0},"r5a.2xlarge":{"hourly_rate":0.604,"upfront_rate":0.0},"m4.2xlarge":{"hourly_rate":0.5667,"upfront_rate":0.0},"t3.micro":{"hourly_rate":0.0144,"upfront_rate":0.0},"r5ad.12xlarge":{"hourly_rate":3.828,"upfront_rate":0.0},"t2.medium":{"hourly_rate":0.0411,"upfront_rate":0.0},"z1d.xlarge":{"hourly_rate":0.36,"upfront_rate":0.0},"x1e.xlarge":{"hourly_rate":0.492,"upfront_rate":0.0},"m5.metal":{"hourly_rate":6.753,"upfront_rate":0.0},"c5.4xlarge":{"hourly_rate":1.064,"upfront_rate":0.0},"c5.2xlarge":{"hourly_rate":0.532,"upfront_rate":0.0},"m5.2xlarge":{"hourly_rate":0.563,"upfront_rate":0.0},"z1d.2xlarge":{"hourly_rate":0.721,"upfront_rate":0.0},"m5d.large":{"hourly_rate":0.149,"upfront_rate":0.0},"m5d.xlarge":{"hourly_rate":0.298,"upfront_rate":0.0},"t2.micro":{"hourly_rate":0.0104,"upfront_rate":0.0},"r5.2xlarge":{"hourly_rate":0.631,"upfront_rate":0.0},"z1d.12xlarge":{"hourly_rate":4.324,"upfront_rate":0.0},"x1e.32xlarge":{"hourly_rate":15.754,"upfront_rate":0.0},"m5.large":{"hourly_rate":0.141,"upfront_rate":0.0},"r5d.large":{"hourly_rate":0.166,"upfront_rate":0.0},"t2.2xlarge":{"hourly_rate":0.2464,"upfront_rate":0.0},"r4.large":{"hourly_rate":0.1578,"upfront_rate":0.0},"c5d.18xlarge":{"hourly_rate":4.981,"upfront_rate":0.0},"t2.small":{"hourly_rate":0.0207,"upfront_rate":0.0},"p3.16xlarge":{"hourly_rate":17.3,"upfront_rate":0.0},"t3.large":{"hourly_rate":0.0689,"upfront_rate":0.0},"p2.16xlarge":{"hourly_rate":11.39,"upfront_rate":0.0},"c5n.4xlarge":{"hourly_rate":1.097,"upfront_rate":0.0},"g3.8xlarge":{"hourly_rate":2.8083,"upfront_rate":0.0},"m4.16xlarge":{"hourly_rate":4.5338,"upfront_rate":0.0},"m5.12xlarge":{"hourly_rate":3.376,"upfront_rate":0.0},"g3.16xlarge":{"hourly_rate":5.6167,"upfront_rate":0.0},"c5n.2xlarge":{"hourly_rate":0.549,"upfront_rate":0.0},"x1.32xlarge":{"hourly_rate":10.819,"upfront_rate":0.0},"m5d.12xlarge":{"hourly_rate":3.573,"upfront_rate":0.0},"c5.xlarge":{"hourly_rate":0.266,"upfront_rate":0.0},"r5ad.large":{"hourly_rate":0.159,"upfront_rate":0.0},"i3.2xlarge":{"hourly_rate":0.716,"upfront_rate":0.0},"m5d.24xlarge":{"hourly_rate":7.146,"upfront_rate":0.0},"t3.2xlarge":{"hourly_rate":0.3124,"upfront_rate":0.0},"m5ad.large":{"hourly_rate":0.144,"upfront_rate":0.0},"i3.metal":{"hourly_rate":5.726,"upfront_rate":0.0},"r5ad.xlarge":{"hourly_rate":0.319,"upfront_rate":0.0},"c4.xlarge":{"hourly_rate":0.286,"upfront_rate":0.0},"m5ad.24xlarge":{"hourly_rate":6.91,"upfront_rate":0.0},"r5d.4xlarge":{"hourly_rate":1.329,"upfront_rate":0.0},"m5d.2xlarge":{"hourly_rate":0.595,"upfront_rate":0.0},"r4.xlarge":{"hourly_rate":0.3157,"upfront_rate":0.0},"r5.large":{"hourly_rate":0.158,"upfront_rate":0.0},"m5ad.2xlarge":{"hourly_rate":0.576,"upfront_rate":0.0},"c5d.large":{"hourly_rate":0.138,"upfront_rate":0.0},"c5d.4xlarge":{"hourly_rate":1.107,"upfront_rate":0.0},"h1.4xlarge":{"hourly_rate":1.256,"upfront_rate":0.0},"x1e.2xlarge":{"hourly_rate":0.985,"upfront_rate":0.0},"r5a.4xlarge":{"hourly_rate":1.208,"upfront_rate":0.0},"i3.xlarge":{"hourly_rate":0.358,"upfront_rate":0.0},"r5a.24xlarge":{"hourly_rate":7.245,"upfront_rate":0.0},"m5a.xlarge":{"hourly_rate":0.271,"upfront_rate":0.0},"r5a.xlarge":{"hourly_rate":0.302,"upfront_rate":0.0},"c5.large":{"hourly_rate":0.133,"upfront_rate":0.0},"d2.8xlarge":{"hourly_rate":2.978,"upfront_rate":0.0},"d2.xlarge":{"hourly_rate":0.432,"upfront_rate":0.0},"r5d.metal":{"hourly_rate":7.975,"upfront_rate":0.0},"z1d.metal":{"hourly_rate":4.324,"upfront_rate":0.0},"m5a.24xlarge":{"hourly_rate":6.502,"upfront_rate":0.0},"m4.4xlarge":{"hourly_rate":1.1334,"upfront_rate":0.0},"c5n.xlarge":{"hourly_rate":0.274,"upfront_rate":0.0},"c4.2xlarge":{"hourly_rate":0.572,"upfront_rate":0.0},"z1d.6xlarge":{"hourly_rate":2.162,"upfront_rate":0.0},"c5.18xlarge":{"hourly_rate":4.789,"upfront_rate":0.0},"c5n.large":{"hourly_rate":0.137,"upfront_rate":0.0},"r5.metal":{"hourly_rate":7.571,"upfront_rate":0.0}}