{"t2.large":{"hourly_rate":0.0681,"upfront_rate":0.0},"m5.4xlarge":{"hourly_rate":1.075,"upfront_rate":0.0},"p2.xlarge":{"hourly_rate":0.643,"upfront_rate":0.0},"m5.xlarge":{"hourly_rate":0.269,"upfront_rate":0.0},"h1.8xlarge":{"hourly_rate":2.376,"upfront_rate":0.0},"r4.8xlarge":{"hourly_rate":2.3878,"upfront_rate":0.0},"m4.large":{"hourly_rate":0.1352,"upfront_rate":0.0},"m5a.large":{"hourly_rate":0.13,"upfront_rate":0.0},"r5.24xlarge":{"hourly_rate":7.159,"upfront_rate":0.0},"p3dn.24xlarge":{"hourly_rate":14.832,"upfront_rate":0.0},"r5ad.4xlarge":{"hourly_rate":1.206,"upfront_rate":0.0},"r5.xlarge":{"hourly_rate":0.298,"upfront_rate":0.0},"c4.4xlarge":{"hourly_rate":1.09,"upfront_rate":0.0},"p3.2xlarge":{"hourly_rate":1.5,"upfront_rate":0.0},"m5d.4xlarge":{"hourly_rate":1.132,"upfront_rate":0.0},"r5.4xlarge":{"hourly_rate":1.193,"upfront_rate":0.0},"t3.xlarge":{"hourly_rate":0.1456,"upfront_rate":0.0},"h1.16xlarge":{"hourly_rate":4.753,"upfront_rate":0.0},"r4.2xlarge":{"hourly_rate":0.597,"upfront_rate":0.0},"m5a.2xlarge":{"hourly_rate":0.519,"upfront_rate":0.0},"i3.4xlarge":{"hourly_rate":1.341,"upfront_rate":0.0},"p2.8xlarge":{"hourly_rate":5.144,"upfront_rate":0.0},"m5a.12xlarge":{"hourly_rate":3.115,"upfront_rate":0.0},"i3.16xlarge":{"hourly_rate":5.363,"upfront_rate":0.0},"r4.4xlarge":{"hourly_rate":1.1939,"upfront_rate":0.0},"m4.10xlarge":{"hourly_rate":2.704,"upfront_rate":0.0},"m4.xlarge":{"hourly_rate":0.2704,"upfront_rate":0.0},"t3.medium":{"hourly_rate":0.0364,"upfront_rate":0.0},"c4.large":{"hourly_rate":0.136,"upfront_rate":0.0},"c4.8xlarge":{"hourly_rate":2.364,"upfront_rate":0.0},"c5n.18xlarge":{"hourly_rate":4.724,"upfront_rate":0.0},"m5ad.4xlarge":{"hourly_rate":1.097,"upfront_rate":0.0},"z1d.3xlarge":{"hourly_rate":1.012,"upfront_rate":0.0},"x1.16xlarge":{"hourly_rate":5.088,"upfront_rate":0.0},"r5d.24xlarge":{"hourly_rate":7.511,"upfront_rate":0.0},"p3.8xlarge":{"hourly_rate":6.001,"upfront_rate":0.0},"x1e.4xlarge":{"hourly_rate":1.808,"upfront_rate":0.0},"x1e.8xlarge":{"hourly_rate":3.617,"upfront_rate":0.0},"t3.nano":{"hourly_rate":0.0068,"upfront_rate":0.0},"c5d.xlarge":{"hourly_rate":0.265,"upfront_rate":0.0},"r5d.12xlarge":{"hourly_rate":3.756,"upfront_rate":0.0},"r5d.2xlarge":{"hourly_rate":0.626,"upfront_rate":0.0},"i3.8xlarge":{"hourly_rate":2.682,"upfront_rate":0.0},"g3.4xlarge":{"hourly_rate":1.317,"upfront_rate":0.0},"m5ad.xlarge":{"hourly_rate":0.274,"upfront_rate":0.0},"c5.9xlarge":{"hourly_rate":2.297,"upfront_rate":0.0},"c5d.2xlarge":{"hourly_rate":0.529,"upfront_rate":0.0},"m5d.metal":{"hourly_rate":6.79,"upfront_rate":0.0},"c5d.9xlarge":{"hourly_rate":2.382,"upfront_rate":0.0},"i3.large":{"hourly_rate":0.168,"upfront_rate":0.0},"r5ad.24xlarge":{"hourly_rate":7.234,"upfront_rate":0.0},"r4.16xlarge":{"hourly_rate":4.7757,"upfront_rate":0.0},"t2.xlarge":{"hourly_rate":0.1212,"upfront_rate":0.0},"r5d.xlarge":{"hourly_rate":0.313,"upfront_rate":0.0},"x1e.16xlarge":{"hourly_rate":7.234,"upfront_rate":0.0},"c5n.9xlarge":{"hourly_rate":2.362,"upfront_rate":0.0},"r5a.large":{"hourly_rate":0.143,"upfront_rate":0.0},"r5.12xlarge":{"hourly_rate":3.58,"upfront_rate":0.0},"h1.2xlarge":{"hourly_rate":0.594,"upfront_rate":0.0},"m5a.4xlarge":{"hourly_rate":1.038,"upfront_rate":0.0},"r5a.12xlarge":{"hourly_rate":3.438,"upfront_rate":0.0},"r5ad.2xlarge":{"hourly_rate":0.603,"upfront_rate":0.0},"g3s.xlarge":{"hourly_rate":0.621,"upfront_rate":0.0},"t2.nano":{"hourly_rate":0.0048,"upfront_rate":0.0},"t3.small":{"hourly_rate":0.0274,"upfront_rate":0.0},"z1d.large":{"hourly_rate":0.169,"upfront_rate":0.0},"m5.24xlarge":{"hourly_rate":6.448,"upfront_rate":0.0},"m5ad.12xlarge":{"hourly_rate":3.292,"upfront_rate":0.0},"r5a.2xlarge":{"hourly_rate":0.573,"upfront_rate":0.0},"m4.2xlarge":{"hourly_rate":0.5408,"upfront_rate":0.0},"t3.micro":{"hourly_rate":0.0137,"upfront_rate":0.0},"r5ad.12xlarge":{"hourly_rate":3.617,"upfront_rate":0.0},"t2.medium":{"hourly_rate":0.038,"upfront_rate":0.0},"z1d.xlarge":{"hourly_rate":0.337,"upfront_rate":0.0},"x1e.xlarge":{"hourly_rate":0.452,"upfront_rate":0.0},"m5.metal":{"hourly_rate":6.448,"upfront_rate":0.0},"c5.4xlarge":{"hourly_rate":1.021,"upfront_rate":0.0},"c5.2xlarge":{"hourly_rate":0.51,"upfront_rate":0.0},"m5.2xlarge":{"hourly_rate":0.537,"upfront_rate":0.0},"z1d.2xlarge":{"hourly_rate":0.675,"upfront_rate":0.0},"m5d.large":{"hourly_rate":0.141,"upfront_rate":0.0},"m5d.xlarge":{"hourly_rate":0.283,"upfront_rate":0.0},"t2.micro":{"hourly_rate":0.0096,"upfront_rate":0.0},"r5.2xlarge":{"hourly_rate":0.597,"upfront_rate":0.0},"z1d.12xlarge":{"hourly_rate":4.05,"upfront_rate":0.0},"x1e.32xlarge":{"hourly_rate":14.467,"upfront_rate":0.0},"m5.large":{"hourly_rate":0.134,"upfront_rate":0.0},"r5d.large":{"hourly_rate":0.156,"upfront_rate":0.0},"t2.2xlarge":{"hourly_rate":0.2224,"upfront_rate":0.0},"r4.large":{"hourly_rate":0.1492,"upfront_rate":0.0},"c5d.18xlarge":{"hourly_rate":4.763,"upfront_rate":0.0},"t2.small":{"hourly_rate":0.0192,"upfront_rate":0.0},"p3.16xlarge":{"hourly_rate":12.001,"upfront_rate":0.0},"t3.large":{"hourly_rate":0.0636,"upfront_rate":0.0},"p2.16xlarge":{"hourly_rate":10.288,"upfront_rate":0.0},"c5n.4xlarge":{"hourly_rate":1.05,"upfront_rate":0.0},"g3.8xlarge":{"hourly_rate":2.634,"upfront_rate":0.0},"m4.16xlarge":{"hourly_rate":4.3264,"upfront_rate":0.0},"m5.12xlarge":{"hourly_rate":3.224,"upfront_rate":0.0},"g3.16xlarge":{"hourly_rate":5.268,"upfront_rate":0.0},"c5n.2xlarge":{"hourly_rate":0.525,"upfront_rate":0.0},"x1.32xlarge":{"hourly_rate":10.176,"upfront_rate":0.0},"m5d.12xlarge":{"hourly_rate":3.395,"upfront_rate":0.0},"c5.xlarge":{"hourly_rate":0.255,"upfront_rate":0.0},"r5ad.large":{"hourly_rate":0.151,"upfront_rate":0.0},"i3.2xlarge":{"hourly_rate":0.67,"upfront_rate":0.0},"m5d.24xlarge":{"hourly_rate":6.79,"upfront_rate":0.0},"t3.2xlarge":{"hourly_rate":0.2912,"upfront_rate":0.0},"m5ad.large":{"hourly_rate":0.137,"upfront_rate":0.0},"i3.metal":{"hourly_rate":5.363,"upfront_rate":0.0},"r5ad.xlarge":{"hourly_rate":0.301,"upfront_rate":0.0},"c4.xlarge":{"hourly_rate":0.273,"upfront_rate":0.0},"m5ad.24xlarge":{"hourly_rate":6.584,"upfront_rate":0.0},"r5d.4xlarge":{"hourly_rate":1.252,"upfront_rate":0.0},"m5d.2xlarge":{"hourly_rate":0.566,"upfront_rate":0.0},"r4.xlarge":{"hourly_rate":0.2985,"upfront_rate":0.0},"r5.large":{"hourly_rate":0.149,"upfront_rate":0.0},"m5ad.2xlarge":{"hourly_rate":0.549,"upfront_rate":0.0},"c5d.large":{"hourly_rate":0.132,"upfront_rate":0.0},"c5d.4xlarge":{"hourly_rate":1.058,"upfront_rate":0.0},"h1.4xlarge":{"hourly_rate":1.188,"upfront_rate":0.0},"x1e.2xlarge":{"hourly_rate":0.904,"upfront_rate":0.0},"r5a.4xlarge":{"hourly_rate":1.146,"upfront_rate":0.0},"i3.xlarge":{"hourly_rate":0.335,"upfront_rate":0.0},"r5a.24xlarge":{"hourly_rate":6.876,"upfront_rate":0.0},"m5a.xlarge":{"hourly_rate":0.26,"upfront_rate":0.0},"r5a.xlarge":{"hourly_rate":0.287,"upfront_rate":0.0},"c5.large":{"hourly_rate":0.128,"upfront_rate":0.0},"r5d.metal":{"hourly_rate":7.511,"upfront_rate":0.0},"z1d.metal":{"hourly_rate":4.05,"upfront_rate":0.0},"m5a.24xlarge":{"hourly_rate":6.231,"upfront_rate":0.0},"m4.4xlarge":{"hourly_rate":1.0816,"upfront_rate":0.0},"c5n.xlarge":{"hourly_rate":0.262,"upfront_rate":0.0},"c4.2xlarge":{"hourly_rate":0.545,"upfront_rate":0.0},"z1d.6xlarge":{"hourly_rate":2.025,"upfront_rate":0.0},"c5.18xlarge":{"hourly_rate":4.594,"upfront_rate":0.0},"c5n.large":{"hourly_rate":0.131,"upfront_rate":0.0},"r5.metal":{"hourly_rate":7.159,"upfront_rate":0.0}}