{"z1d.xlarge":{"hourly_rate":0.0,"upfront_rate":5431.0},"t3.micro":{"hourly_rate":0.0,"upfront_rate":236.0},"t3.medium":{"hourly_rate":0.0,"upfront_rate":1157.0},"g3.4xlarge":{"hourly_rate":0.0,"upfront_rate":19691.0},"r4.2xlarge":{"hourly_rate":0.0,"upfront_rate":6552.0},"m4.2xlarge":{"hourly_rate":0.0,"upfront_rate":6030.0},"m5d.xlarge":{"hourly_rate":0.0,"upfront_rate":3758.0},"i3.2xlarge":{"hourly_rate":0.0,"upfront_rate":8342.0},"c5.xlarge":{"hourly_rate":0.0,"upfront_rate":2942.0},"c5d.18xlarge":{"hourly_rate":0.0,"upfront_rate":46579.0},"t2.micro":{"hourly_rate":0.0,"upfront_rate":359.0},"m5.24xlarge":{"hourly_rate":0.0,"upfront_rate":63269.0},"r5d.24xlarge":{"hourly_rate":0.0,"upfront_rate":82222.0},"t3.small":{"hourly_rate":0.0,"upfront_rate":579.0},"t2.xlarge":{"hourly_rate":0.0,"upfront_rate":3211.0},"m4.large":{"hourly_rate":0.0,"upfront_rate":2028.0},"r5.xlarge":{"hourly_rate":0.0,"upfront_rate":4088.0},"m5.large":{"hourly_rate":0.0,"upfront_rate":1998.0},"z1d.3xlarge":{"hourly_rate":0.0,"upfront_rate":14166.0},"r5.4xlarge":{"hourly_rate":0.0,"upfront_rate":13039.0},"t2.small":{"hourly_rate":0.0,"upfront_rate":833.0},"z1d.12xlarge":{"hourly_rate":0.0,"upfront_rate":52406.0},"t3.large":{"hourly_rate":0.0,"upfront_rate":1723.0},"c5.2xlarge":{"hourly_rate":0.0,"upfront_rate":5190.0},"r4.large":{"hourly_rate":0.0,"upfront_rate":2158.0},"z1d.6xlarge":{"hourly_rate":0.0,"upfront_rate":26912.0},"c4.xlarge":{"hourly_rate":0.0,"upfront_rate":3535.0},"c5d.9xlarge":{"hourly_rate":0.0,"upfront_rate":23637.0},"r5d.large":{"hourly_rate":0.0,"upfront_rate":2275.0},"i3.8xlarge":{"hourly_rate":0.0,"upfront_rate":31286.0},"r5.large":{"hourly_rate":0.0,"upfront_rate":2044.0},"i3.4xlarge":{"hourly_rate":0.0,"upfront_rate":15990.0},"r4.8xlarge":{"hourly_rate":0.0,"upfront_rate":24124.0},"c5d.2xlarge":{"hourly_rate":0.0,"upfront_rate":5792.0},"t3.2xlarge":{"hourly_rate":0.0,"upfront_rate":5946.0},"t3.xlarge":{"hourly_rate":0.0,"upfront_rate":3446.0},"m5.4xlarge":{"hourly_rate":0.0,"upfront_rate":11123.0},"t2.large":{"hourly_rate":0.0,"upfront_rate":1953.0},"z1d.2xlarge":{"hourly_rate":0.0,"upfront_rate":9917.0},"c5.18xlarge":{"hourly_rate":0.0,"upfront_rate":41154.0},"t3.nano":{"hourly_rate":0.0,"upfront_rate":166.0},"m4.16xlarge":{"hourly_rate":0.0,"upfront_rate":43381.0},"r5d.4xlarge":{"hourly_rate":0.0,"upfront_rate":14886.0},"m5.xlarge":{"hourly_rate":0.0,"upfront_rate":3301.0},"i3.metal":{"hourly_rate":0.0,"upfront_rate":61879.0},"r5d.metal":{"hourly_rate":0.0,"upfront_rate":82222.0},"r5d.xlarge":{"hourly_rate":0.0,"upfront_rate":4549.0},"r4.4xlarge":{"hourly_rate":0.0,"upfront_rate":12409.0},"z1d.large":{"hourly_rate":0.0,"upfront_rate":2716.0},"c5d.4xlarge":{"hourly_rate":0.0,"upfront_rate":10891.0},"t2.nano":{"hourly_rate":0.0,"upfront_rate":281.0},"r5.24xlarge":{"hourly_rate":0.0,"upfront_rate":71141.0},"m5d.4xlarge":{"hourly_rate":0.0,"upfront_rate":12951.0},"c4.8xlarge":{"hourly_rate":0.0,"upfront_rate":23446.0},"c5d.large":{"hourly_rate":0.0,"upfront_rate":1969.0},"r5.2xlarge":{"hourly_rate":0.0,"upfront_rate":7229.0},"c5.9xlarge":{"hourly_rate":0.0,"upfront_rate":20924.0},"m5d.2xlarge":{"hourly_rate":0.0,"upfront_rate":6823.0},"t2.medium":{"hourly_rate":0.0,"upfront_rate":1323.0},"i3.16xlarge":{"hourly_rate":0.0,"upfront_rate":61879.0},"d2.8xlarge":{"hourly_rate":0.0,"upfront_rate":53806.0},"c5.4xlarge":{"hourly_rate":0.0,"upfront_rate":9685.0},"m4.xlarge":{"hourly_rate":0.0,"upfront_rate":3362.0},"c5.large":{"hourly_rate":0.0,"upfront_rate":1818.0},"c4.4xlarge":{"hourly_rate":0.0,"upfront_rate":12082.0},"d2.2xlarge":{"hourly_rate":0.0,"upfront_rate":13984.0},"m5d.large":{"hourly_rate":0.0,"upfront_rate":2226.0},"g3.8xlarge":{"hourly_rate":0.0,"upfront_rate":38687.0},"r5.metal":{"hourly_rate":0.0,"upfront_rate":71141.0},"c5d.xlarge":{"hourly_rate":0.0,"upfront_rate":3243.0},"m5.metal":{"hourly_rate":0.0,"upfront_rate":63269.0},"m4.10xlarge":{"hourly_rate":0.0,"upfront_rate":27374.0},"c4.large":{"hourly_rate":0.0,"upfront_rate":2102.0},"r5d.12xlarge":{"hourly_rate":0.0,"upfront_rate":41821.0},"m5d.24xlarge":{"hourly_rate":0.0,"upfront_rate":74239.0},"m5d.12xlarge":{"hourly_rate":0.0,"upfront_rate":37466.0},"r4.xlarge":{"hourly_rate":0.0,"upfront_rate":3623.0},"r4.16xlarge":{"hourly_rate":0.0,"upfront_rate":47555.0},"c4.2xlarge":{"hourly_rate":0.0,"upfront_rate":6400.0},"m5.2xlarge":{"hourly_rate":0.0,"upfront_rate":5909.0},"r5d.2xlarge":{"hourly_rate":0.0,"upfront_rate":8152.0},"i3.large":{"hourly_rate":0.0,"upfront_rate":2606.0},"r5.12xlarge":{"hourly_rate":0.0,"upfront_rate":36280.0},"d2.xlarge":{"hourly_rate":0.0,"upfront_rate":7339.0},"g3.16xlarge":{"hourly_rate":0.0,"upfront_rate":76680.0},"m4.4xlarge":{"hourly_rate":0.0,"upfront_rate":11366.0},"d2.4xlarge":{"hourly_rate":0.0,"upfront_rate":27250.0},"z1d.metal":{"hourly_rate":0.0,"upfront_rate":52406.0},"m5.12xlarge":{"hourly_rate":0.0,"upfront_rate":31981.0},"i3.xlarge":{"hourly_rate":0.0,"upfront_rate":4518.0},"t2.2xlarge":{"hourly_rate":0.0,"upfront_rate":5729.0}}