{"t2.large":{"hourly_rate":0.0845,"upfront_rate":0.0},"c5.large":{"hourly_rate":0.093,"upfront_rate":0.0},"t3.nano":{"hourly_rate":0.0048,"upfront_rate":0.0},"c4.large":{"hourly_rate":0.11,"upfront_rate":0.0},"t3.2xlarge":{"hourly_rate":0.3088,"upfront_rate":0.0},"i3.xlarge":{"hourly_rate":0.391,"upfront_rate":0.0},"t2.2xlarge":{"hourly_rate":0.338,"upfront_rate":0.0},"t3.large":{"hourly_rate":0.0772,"upfront_rate":0.0},"m5.xlarge":{"hourly_rate":0.181,"upfront_rate":0.0},"t3.small":{"hourly_rate":0.0193,"upfront_rate":0.0},"c4.4xlarge":{"hourly_rate":0.882,"upfront_rate":0.0},"m4.large":{"hourly_rate":0.0903,"upfront_rate":0.0},"r4.8xlarge":{"hourly_rate":2.8224,"upfront_rate":0.0},"c5.2xlarge":{"hourly_rate":0.374,"upfront_rate":0.0},"r4.xlarge":{"hourly_rate":0.3528,"upfront_rate":0.0},"c4.2xlarge":{"hourly_rate":0.441,"upfront_rate":0.0},"c5.9xlarge":{"hourly_rate":1.681,"upfront_rate":0.0},"t3.micro":{"hourly_rate":0.0096,"upfront_rate":0.0},"m4.2xlarge":{"hourly_rate":0.3612,"upfront_rate":0.0},"c4.8xlarge":{"hourly_rate":1.764,"upfront_rate":0.0},"m5.4xlarge":{"hourly_rate":0.722,"upfront_rate":0.0},"i3.2xlarge":{"hourly_rate":0.781,"upfront_rate":0.0},"t3.medium":{"hourly_rate":0.0386,"upfront_rate":0.0},"i3.16xlarge":{"hourly_rate":6.25,"upfront_rate":0.0},"c4.xlarge":{"hourly_rate":0.22,"upfront_rate":0.0},"x1.16xlarge":{"hourly_rate":8.014,"upfront_rate":0.0},"c5.4xlarge":{"hourly_rate":0.747,"upfront_rate":0.0},"r4.large":{"hourly_rate":0.1764,"upfront_rate":0.0},"t2.medium":{"hourly_rate":0.0423,"upfront_rate":0.0},"t2.small":{"hourly_rate":0.0211,"upfront_rate":0.0},"i3.large":{"hourly_rate":0.195,"upfront_rate":0.0},"r4.2xlarge":{"hourly_rate":0.7056,"upfront_rate":0.0},"m4.10xlarge":{"hourly_rate":1.806,"upfront_rate":0.0},"m4.4xlarge":{"hourly_rate":0.7224,"upfront_rate":0.0},"m5.large":{"hourly_rate":0.09,"upfront_rate":0.0},"m5.12xlarge":{"hourly_rate":2.167,"upfront_rate":0.0},"m5.2xlarge":{"hourly_rate":0.361,"upfront_rate":0.0},"m4.16xlarge":{"hourly_rate":2.8896,"upfront_rate":0.0},"t2.micro":{"hourly_rate":0.0106,"upfront_rate":0.0},"c5.xlarge":{"hourly_rate":0.187,"upfront_rate":0.0},"t3.xlarge":{"hourly_rate":0.1544,"upfront_rate":0.0},"x1.32xlarge":{"hourly_rate":16.029,"upfront_rate":0.0},"c5.18xlarge":{"hourly_rate":3.363,"upfront_rate":0.0},"m4.xlarge":{"hourly_rate":0.1806,"upfront_rate":0.0},"t2.nano":{"hourly_rate":0.0053,"upfront_rate":0.0},"m5.24xlarge":{"hourly_rate":4.334,"upfront_rate":0.0},"r4.4xlarge":{"hourly_rate":1.4112,"upfront_rate":0.0},"t2.xlarge":{"hourly_rate":0.169,"upfront_rate":0.0},"r4.16xlarge":{"hourly_rate":5.6448,"upfront_rate":0.0},"i3.8xlarge":{"hourly_rate":3.125,"upfront_rate":0.0},"i3.4xlarge":{"hourly_rate":1.562,"upfront_rate":0.0}}