{"m5d.xlarge":{"hourly_rate":0.0,"upfront_rate":21256.0},"m5d.2xlarge":{"hourly_rate":0.0,"upfront_rate":42511.0},"m5.large":{"hourly_rate":0.0,"upfront_rate":16658.0},"i3.2xlarge":{"hourly_rate":0.0,"upfront_rate":44851.0},"c5.xlarge":{"hourly_rate":0.0,"upfront_rate":20175.0},"x1e.16xlarge":{"hourly_rate":0.0,"upfront_rate":449733.0},"c4.2xlarge":{"hourly_rate":0.0,"upfront_rate":56822.0},"x1e.xlarge":{"hourly_rate":0.0,"upfront_rate":28108.0},"c5d.large":{"hourly_rate":0.0,"upfront_rate":16583.0},"r4.2xlarge":{"hourly_rate":0.0,"upfront_rate":42482.0},"r5a.4xlarge":{"hourly_rate":0.0,"upfront_rate":83446.0},"c5d.2xlarge":{"hourly_rate":0.0,"upfront_rate":41102.0},"m5.metal":{"hourly_rate":0.0,"upfront_rate":496820.0},"z1d.2xlarge":{"hourly_rate":0.0,"upfront_rate":45207.0},"m4.xlarge":{"hourly_rate":0.0,"upfront_rate":20767.0},"c4.large":{"hourly_rate":0.0,"upfront_rate":23809.0},"z1d.xlarge":{"hourly_rate":0.0,"upfront_rate":22603.0},"r4.large":{"hourly_rate":0.0,"upfront_rate":16928.0},"c5.18xlarge":{"hourly_rate":0.0,"upfront_rate":363148.0},"r5a.xlarge":{"hourly_rate":0.0,"upfront_rate":20861.0},"c5.9xlarge":{"hourly_rate":0.0,"upfront_rate":181574.0},"r5d.xlarge":{"hourly_rate":0.0,"upfront_rate":21759.0},"i3.large":{"hourly_rate":0.0,"upfront_rate":17520.0},"r5d.large":{"hourly_rate":0.0,"upfront_rate":17187.0},"z1d.large":{"hourly_rate":0.0,"upfront_rate":17609.0},"r5.24xlarge":{"hourly_rate":0.0,"upfront_rate":508959.0},"c5.2xlarge":{"hourly_rate":0.0,"upfront_rate":40350.0},"r5.xlarge":{"hourly_rate":0.0,"upfront_rate":21207.0},"r5d.24xlarge":{"hourly_rate":0.0,"upfront_rate":522223.0},"r5a.24xlarge":{"hourly_rate":0.0,"upfront_rate":500675.0},"m5.4xlarge":{"hourly_rate":0.0,"upfront_rate":82803.0},"r4.16xlarge":{"hourly_rate":0.0,"upfront_rate":339855.0},"m5a.24xlarge":{"hourly_rate":0.0,"upfront_rate":489025.0},"r5d.12xlarge":{"hourly_rate":0.0,"upfront_rate":261111.0},"z1d.metal":{"hourly_rate":0.0,"upfront_rate":271241.0},"r5a.12xlarge":{"hourly_rate":0.0,"upfront_rate":250337.0},"m5.12xlarge":{"hourly_rate":0.0,"upfront_rate":248410.0},"r5.12xlarge":{"hourly_rate":0.0,"upfront_rate":254479.0},"m5a.4xlarge":{"hourly_rate":0.0,"upfront_rate":81504.0},"z1d.6xlarge":{"hourly_rate":0.0,"upfront_rate":135620.0},"t3.2xlarge":{"hourly_rate":0.0,"upfront_rate":34704.0},"z1d.3xlarge":{"hourly_rate":0.0,"upfront_rate":67810.0},"r5.2xlarge":{"hourly_rate":0.0,"upfront_rate":42413.0},"c4.xlarge":{"hourly_rate":0.0,"upfront_rate":28592.0},"m4.10xlarge":{"hourly_rate":0.0,"upfront_rate":207671.0},"r5a.2xlarge":{"hourly_rate":0.0,"upfront_rate":41723.0},"c5d.4xlarge":{"hourly_rate":0.0,"upfront_rate":82205.0},"r5a.large":{"hourly_rate":0.0,"upfront_rate":16738.0},"i3.16xlarge":{"hourly_rate":0.0,"upfront_rate":358811.0},"c5.4xlarge":{"hourly_rate":0.0,"upfront_rate":80699.0},"m5.2xlarge":{"hourly_rate":0.0,"upfront_rate":41402.0},"i3.4xlarge":{"hourly_rate":0.0,"upfront_rate":89703.0},"x1.32xlarge":{"hourly_rate":0.0,"upfront_rate":728936.0},"t3.xlarge":{"hourly_rate":0.0,"upfront_rate":17352.0},"x1e.4xlarge":{"hourly_rate":0.0,"upfront_rate":112433.0},"m5d.large":{"hourly_rate":0.0,"upfront_rate":16935.0},"c4.8xlarge":{"hourly_rate":0.0,"upfront_rate":190047.0},"m4.large":{"hourly_rate":0.0,"upfront_rate":16691.0},"x1.16xlarge":{"hourly_rate":0.0,"upfront_rate":364468.0},"r4.4xlarge":{"hourly_rate":0.0,"upfront_rate":84964.0},"i3.8xlarge":{"hourly_rate":0.0,"upfront_rate":179406.0},"m4.4xlarge":{"hourly_rate":0.0,"upfront_rate":83068.0},"r4.xlarge":{"hourly_rate":0.0,"upfront_rate":21241.0},"m5a.large":{"hourly_rate":0.0,"upfront_rate":16495.0},"c5d.18xlarge":{"hourly_rate":0.0,"upfront_rate":369922.0},"r5d.4xlarge":{"hourly_rate":0.0,"upfront_rate":87037.0},"m5a.2xlarge":{"hourly_rate":0.0,"upfront_rate":40752.0},"r5.large":{"hourly_rate":0.0,"upfront_rate":16911.0},"x1e.2xlarge":{"hourly_rate":0.0,"upfront_rate":56217.0},"m5a.xlarge":{"hourly_rate":0.0,"upfront_rate":20376.0},"m5d.24xlarge":{"hourly_rate":0.0,"upfront_rate":510136.0},"r5.4xlarge":{"hourly_rate":0.0,"upfront_rate":84826.0},"z1d.12xlarge":{"hourly_rate":0.0,"upfront_rate":271241.0},"c5d.9xlarge":{"hourly_rate":0.0,"upfront_rate":184961.0},"i3.xlarge":{"hourly_rate":0.0,"upfront_rate":22426.0},"r4.8xlarge":{"hourly_rate":0.0,"upfront_rate":169928.0},"m4.2xlarge":{"hourly_rate":0.0,"upfront_rate":41534.0},"r5d.2xlarge":{"hourly_rate":0.0,"upfront_rate":43519.0},"m5d.metal":{"hourly_rate":0.0,"upfront_rate":510136.0},"m5d.12xlarge":{"hourly_rate":0.0,"upfront_rate":255068.0},"m5.xlarge":{"hourly_rate":0.0,"upfront_rate":20701.0},"c5d.xlarge":{"hourly_rate":0.0,"upfront_rate":20551.0},"x1e.8xlarge":{"hourly_rate":0.0,"upfront_rate":224867.0},"x1e.32xlarge":{"hourly_rate":0.0,"upfront_rate":899467.0},"c5.large":{"hourly_rate":0.0,"upfront_rate":16395.0},"c4.4xlarge":{"hourly_rate":0.0,"upfront_rate":95013.0},"m5.24xlarge":{"hourly_rate":0.0,"upfront_rate":496820.0},"m4.16xlarge":{"hourly_rate":0.0,"upfront_rate":332273.0},"m5a.12xlarge":{"hourly_rate":0.0,"upfront_rate":244512.0},"m5d.4xlarge":{"hourly_rate":0.0,"upfront_rate":85023.0}}