{"c4.8xlarge":{"hourly_rate":0.0,"upfront_rate":337431.0},"c5d.18xlarge":{"hourly_rate":0.0,"upfront_rate":369069.0},"r5d.xlarge":{"hourly_rate":0.0,"upfront_rate":21683.0},"t3.2xlarge":{"hourly_rate":0.0,"upfront_rate":34363.0},"r4.xlarge":{"hourly_rate":0.0,"upfront_rate":21122.0},"c5.xlarge":{"hourly_rate":0.0,"upfront_rate":20100.0},"i3.large":{"hourly_rate":0.0,"upfront_rate":17461.0},"r5d.24xlarge":{"hourly_rate":0.0,"upfront_rate":520392.0},"m5.metal":{"hourly_rate":0.0,"upfront_rate":492411.0},"m4.2xlarge":{"hourly_rate":0.0,"upfront_rate":41179.0},"c5d.4xlarge":{"hourly_rate":0.0,"upfront_rate":82015.0},"r5.2xlarge":{"hourly_rate":0.0,"upfront_rate":42264.0},"m5.24xlarge":{"hourly_rate":0.0,"upfront_rate":492411.0},"m5d.2xlarge":{"hourly_rate":0.0,"upfront_rate":42123.0},"m4.4xlarge":{"hourly_rate":0.0,"upfront_rate":82358.0},"c5d.large":{"hourly_rate":0.0,"upfront_rate":16559.0},"i3.2xlarge":{"hourly_rate":0.0,"upfront_rate":44614.0},"r5.24xlarge":{"hourly_rate":0.0,"upfront_rate":507167.0},"m4.xlarge":{"hourly_rate":0.0,"upfront_rate":20589.0},"m5.xlarge":{"hourly_rate":0.0,"upfront_rate":20517.0},"m4.large":{"hourly_rate":0.0,"upfront_rate":16602.0},"x1.32xlarge":{"hourly_rate":0.0,"upfront_rate":706546.0},"r5.4xlarge":{"hourly_rate":0.0,"upfront_rate":84528.0},"m5.large":{"hourly_rate":0.0,"upfront_rate":16566.0},"r4.16xlarge":{"hourly_rate":0.0,"upfront_rate":337960.0},"t3.xlarge":{"hourly_rate":0.0,"upfront_rate":17181.0},"m5d.12xlarge":{"hourly_rate":0.0,"upfront_rate":252741.0},"r5d.large":{"hourly_rate":0.0,"upfront_rate":17149.0},"r4.large":{"hourly_rate":0.0,"upfront_rate":16868.0},"r5.12xlarge":{"hourly_rate":0.0,"upfront_rate":253584.0},"c5.2xlarge":{"hourly_rate":0.0,"upfront_rate":40200.0},"r5d.2xlarge":{"hourly_rate":0.0,"upfront_rate":43366.0},"r4.2xlarge":{"hourly_rate":0.0,"upfront_rate":42245.0},"r5.large":{"hourly_rate":0.0,"upfront_rate":16873.0},"r5d.12xlarge":{"hourly_rate":0.0,"upfront_rate":260196.0},"c4.large":{"hourly_rate":0.0,"upfront_rate":33753.0},"r5.xlarge":{"hourly_rate":0.0,"upfront_rate":21132.0},"m4.10xlarge":{"hourly_rate":0.0,"upfront_rate":205894.0},"x1.16xlarge":{"hourly_rate":0.0,"upfront_rate":353273.0},"c4.4xlarge":{"hourly_rate":0.0,"upfront_rate":151502.0},"c5.4xlarge":{"hourly_rate":0.0,"upfront_rate":80400.0},"i3.16xlarge":{"hourly_rate":0.0,"upfront_rate":356915.0},"m5.4xlarge":{"hourly_rate":0.0,"upfront_rate":82068.0},"i3.8xlarge":{"hourly_rate":0.0,"upfront_rate":178457.0},"m4.16xlarge":{"hourly_rate":0.0,"upfront_rate":329430.0},"m5d.xlarge":{"hourly_rate":0.0,"upfront_rate":21062.0},"r4.4xlarge":{"hourly_rate":0.0,"upfront_rate":84490.0},"m5d.4xlarge":{"hourly_rate":0.0,"upfront_rate":84247.0},"i3.xlarge":{"hourly_rate":0.0,"upfront_rate":22307.0},"m5.12xlarge":{"hourly_rate":0.0,"upfront_rate":246205.0},"r5d.4xlarge":{"hourly_rate":0.0,"upfront_rate":86732.0},"c5d.9xlarge":{"hourly_rate":0.0,"upfront_rate":184535.0},"r4.8xlarge":{"hourly_rate":0.0,"upfront_rate":168980.0},"m5.2xlarge":{"hourly_rate":0.0,"upfront_rate":41034.0},"m5d.24xlarge":{"hourly_rate":0.0,"upfront_rate":505481.0},"c4.2xlarge":{"hourly_rate":0.0,"upfront_rate":75751.0},"c5d.2xlarge":{"hourly_rate":0.0,"upfront_rate":41008.0},"m5d.large":{"hourly_rate":0.0,"upfront_rate":16838.0},"c5.9xlarge":{"hourly_rate":0.0,"upfront_rate":180900.0},"i3.4xlarge":{"hourly_rate":0.0,"upfront_rate":89229.0},"c5d.xlarge":{"hourly_rate":0.0,"upfront_rate":20504.0},"c4.xlarge":{"hourly_rate":0.0,"upfront_rate":37889.0},"c5.large":{"hourly_rate":0.0,"upfront_rate":16357.0},"c5.18xlarge":{"hourly_rate":0.0,"upfront_rate":361800.0}}