{"r5.4xlarge":{"hourly_rate":0.322,"upfront_rate":2817.0},"m5d.2xlarge":{"hourly_rate":0.161,"upfront_rate":1408.0},"r5.large":{"hourly_rate":0.04,"upfront_rate":352.0},"m5d.12xlarge":{"hourly_rate":0.964,"upfront_rate":8447.0},"m5.metal":{"hourly_rate":1.637,"upfront_rate":14341.0},"c5d.large":{"hourly_rate":0.034,"upfront_rate":299.0},"c5d.9xlarge":{"hourly_rate":0.615,"upfront_rate":5387.0},"i3.8xlarge":{"hourly_rate":0.849,"upfront_rate":7438.0},"r5.12xlarge":{"hourly_rate":0.965,"upfront_rate":8452.0},"m5d.xlarge":{"hourly_rate":0.08,"upfront_rate":704.0},"m5.4xlarge":{"hourly_rate":0.273,"upfront_rate":2390.0},"t3.micro":{"hourly_rate":0.0037,"upfront_rate":32.0},"c5.large":{"hourly_rate":0.03,"upfront_rate":261.0},"c5.18xlarge":{"hourly_rate":1.075,"upfront_rate":9413.0},"m5.xlarge":{"hourly_rate":0.068,"upfront_rate":598.0},"c5d.2xlarge":{"hourly_rate":0.137,"upfront_rate":1197.0},"t3.large":{"hourly_rate":0.0293,"upfront_rate":257.0},"m5.2xlarge":{"hourly_rate":0.136,"upfront_rate":1195.0},"t3.2xlarge":{"hourly_rate":0.1172,"upfront_rate":1026.0},"m5.large":{"hourly_rate":0.034,"upfront_rate":299.0},"c5.xlarge":{"hourly_rate":0.06,"upfront_rate":523.0},"c5.4xlarge":{"hourly_rate":0.239,"upfront_rate":2092.0},"m5.24xlarge":{"hourly_rate":1.637,"upfront_rate":14341.0},"c5d.xlarge":{"hourly_rate":0.068,"upfront_rate":599.0},"r5d.large":{"hourly_rate":0.046,"upfront_rate":404.0},"i3.2xlarge":{"hourly_rate":0.212,"upfront_rate":1860.0},"r5d.24xlarge":{"hourly_rate":2.214,"upfront_rate":19393.0},"r5.metal":{"hourly_rate":1.93,"upfront_rate":16903.0},"m5d.24xlarge":{"hourly_rate":1.929,"upfront_rate":16895.0},"d2.xlarge":{"hourly_rate":0.181,"upfront_rate":1590.0},"d2.2xlarge":{"hourly_rate":0.363,"upfront_rate":3180.0},"i3.4xlarge":{"hourly_rate":0.425,"upfront_rate":3719.0},"c5.9xlarge":{"hourly_rate":0.537,"upfront_rate":4706.0},"r5.2xlarge":{"hourly_rate":0.161,"upfront_rate":1409.0},"c5d.18xlarge":{"hourly_rate":1.23,"upfront_rate":10773.0},"r5.24xlarge":{"hourly_rate":1.93,"upfront_rate":16903.0},"r5d.metal":{"hourly_rate":2.214,"upfront_rate":19393.0},"t3.xlarge":{"hourly_rate":0.0586,"upfront_rate":513.0},"d2.8xlarge":{"hourly_rate":1.452,"upfront_rate":12718.0},"d2.4xlarge":{"hourly_rate":0.726,"upfront_rate":6359.0},"c5.2xlarge":{"hourly_rate":0.119,"upfront_rate":1046.0},"t3.medium":{"hourly_rate":0.0146,"upfront_rate":128.0},"r5d.12xlarge":{"hourly_rate":1.107,"upfront_rate":9697.0},"i3.large":{"hourly_rate":0.053,"upfront_rate":465.0},"r5d.xlarge":{"hourly_rate":0.092,"upfront_rate":808.0},"m5.12xlarge":{"hourly_rate":0.819,"upfront_rate":7170.0},"i3.16xlarge":{"hourly_rate":1.698,"upfront_rate":14876.0},"m5d.4xlarge":{"hourly_rate":0.321,"upfront_rate":2816.0},"c5d.4xlarge":{"hourly_rate":0.273,"upfront_rate":2394.0},"i3.xlarge":{"hourly_rate":0.106,"upfront_rate":930.0},"r5d.2xlarge":{"hourly_rate":0.184,"upfront_rate":1616.0},"t3.small":{"hourly_rate":0.0073,"upfront_rate":64.0},"m5d.large":{"hourly_rate":0.04,"upfront_rate":352.0},"r5d.4xlarge":{"hourly_rate":0.369,"upfront_rate":3232.0},"m5d.metal":{"hourly_rate":1.929,"upfront_rate":16895.0},"t3.nano":{"hourly_rate":0.0018,"upfront_rate":16.0},"r5.xlarge":{"hourly_rate":0.08,"upfront_rate":704.0}}